pybatman/__init.py__
pybatman/functions.py
pybatman/data/AA_matrices/batman.csv
pybatman/data/AA_matrices/blosum100.csv
pybatman/data/AA_matrices/blosum30.csv
pybatman/data/AA_matrices/blosum35.csv
pybatman/data/AA_matrices/blosum40.csv
pybatman/data/AA_matrices/blosum45.csv
pybatman/data/AA_matrices/blosum50.csv
pybatman/data/AA_matrices/blosum55.csv
pybatman/data/AA_matrices/blosum60.csv
pybatman/data/AA_matrices/blosum62.csv
pybatman/data/AA_matrices/blosum65.csv
pybatman/data/AA_matrices/blosum70.csv
pybatman/data/AA_matrices/blosum75.csv
pybatman/data/AA_matrices/blosum80.csv
pybatman/data/AA_matrices/blosum85.csv
pybatman/data/AA_matrices/blosum90.csv
pybatman/data/AA_matrices/dayhoff.csv
pybatman/data/AA_matrices/gonnet.csv
pybatman/data/AA_matrices/hamming.csv
pybatman/data/AA_matrices/pam10.csv
pybatman/data/AA_matrices/pam100.csv
pybatman/data/AA_matrices/pam110.csv
pybatman/data/AA_matrices/pam120.csv
pybatman/data/AA_matrices/pam130.csv
pybatman/data/AA_matrices/pam140.csv
pybatman/data/AA_matrices/pam150.csv
pybatman/data/AA_matrices/pam160.csv
pybatman/data/AA_matrices/pam170.csv
pybatman/data/AA_matrices/pam180.csv
pybatman/data/AA_matrices/pam190.csv
pybatman/data/AA_matrices/pam20.csv
pybatman/data/AA_matrices/pam200.csv
pybatman/data/AA_matrices/pam210.csv
pybatman/data/AA_matrices/pam220.csv
pybatman/data/AA_matrices/pam230.csv
pybatman/data/AA_matrices/pam240.csv
pybatman/data/AA_matrices/pam250.csv
pybatman/data/AA_matrices/pam260.csv
pybatman/data/AA_matrices/pam270.csv
pybatman/data/AA_matrices/pam280.csv
pybatman/data/AA_matrices/pam290.csv
pybatman/data/AA_matrices/pam30.csv
pybatman/data/AA_matrices/pam300.csv
pybatman/data/AA_matrices/pam310.csv
pybatman/data/AA_matrices/pam320.csv
pybatman/data/AA_matrices/pam330.csv
pybatman/data/AA_matrices/pam340.csv
pybatman/data/AA_matrices/pam350.csv
pybatman/data/AA_matrices/pam360.csv
pybatman/data/AA_matrices/pam370.csv
pybatman/data/AA_matrices/pam380.csv
pybatman/data/AA_matrices/pam390.csv
pybatman-1.0.1.dist-info/METADATA
pybatman-1.0.1.dist-info/WHEEL
pybatman-1.0.1.dist-info/licenses/LICENSE.txt
pybatman-1.0.1.dist-info/RECORD
