Metadata-Version: 2.4
Name: pybatman
Version: 1.0.1
Summary: Package for predicting peptide mutation effects on T cell receptor activation.
Project-URL: Homepage, https://github.com/meyer-lab-cshl/BATMAN
Project-URL: Bug Tracker, https://github.com/meyer-lab-cshl/BATMAN/issues
Author-email: Amitava Banerjee <amitavab@cshl.edu>
License-File: LICENSE.txt
Classifier: License :: OSI Approved :: BSD License
Classifier: Operating System :: OS Independent
Classifier: Programming Language :: Python :: 3
Requires-Python: >=3.11
Requires-Dist: arviz>=0.21.0
Requires-Dist: numpy>=2.0.2
Requires-Dist: openpyxl>=3.1.5
Requires-Dist: pandas>=2.2.2
Requires-Dist: pymc>=5.23.0
